picasso/__init__.py
picasso/config.py
picasso/picasso.py
picasso/examples/keras/config.py
picasso/examples/keras/model.py
picasso/examples/keras/data-volume/MNIST-weights.hdf5
picasso/examples/keras/data-volume/model.json
picasso/examples/keras-vgg16/config.py
picasso/examples/keras-vgg16/model.py
picasso/examples/keras-vgg16/prepare_model.py
picasso/examples/tensorflow/config.py
picasso/examples/tensorflow/model.py
picasso/examples/tensorflow/data-volume/checkpoint
picasso/examples/tensorflow/data-volume/convolutional.ckpt.data-00000-of-00001
picasso/examples/tensorflow/data-volume/convolutional.ckpt.index
picasso/examples/tensorflow/data-volume/convolutional.ckpt.meta
picasso/models/__init__.py
picasso/models/base.py
picasso/models/keras.py
picasso/models/tensorflow.py
picasso/static/favicon.ico
picasso/static/style.css
picasso/templates/404.html
picasso/templates/500.html
picasso/templates/ClassProbabilities.html
picasso/templates/PartialOcclusion.html
picasso/templates/SaliencyMaps.html
picasso/templates/layout.html
picasso/templates/result.html
picasso/templates/select_files.html
picasso/templates/select_visualization.html
picasso/templates/settings.html
picasso/visualizations/__init__.py
picasso/visualizations/base.py
picasso/visualizations/class_probabilities.py
picasso/visualizations/partial_occlusion.py
picasso/visualizations/saliency_maps.py
picasso_viz-0.2.0.dist-info/DESCRIPTION.rst
picasso_viz-0.2.0.dist-info/METADATA
picasso_viz-0.2.0.dist-info/RECORD
picasso_viz-0.2.0.dist-info/WHEEL
picasso_viz-0.2.0.dist-info/entry_points.txt
picasso_viz-0.2.0.dist-info/metadata.json
picasso_viz-0.2.0.dist-info/top_level.txt
