Metadata-Version: 2.0
Name: picasso-viz
Version: 0.2.0
Summary: A CNN model visualizer
Home-page: https://github.com/merantix/picasso
Author: Ryan Henderson
Author-email: ryan@merantix.com
License: Eclipse Public License 1.0 (EPL-1.0)
Keywords: picasso
Platform: UNKNOWN
Classifier: Development Status :: 2 - Pre-Alpha
Classifier: Intended Audience :: Developers
Classifier: License :: OSI Approved :: Eclipse Public License 1.0 (EPL-1.0)
Classifier: Natural Language :: English
Classifier: Programming Language :: Python :: 3.5
Requires-Dist: click (>=6.7)
Requires-Dist: cycler (>=0.10.0)
Requires-Dist: Flask (>=0.12)
Requires-Dist: h5py (>=2.6.0)
Requires-Dist: itsdangerous (>=0.24)
Requires-Dist: Jinja2 (>=2.9.5)
Requires-Dist: Keras (>=1.2.2)
Requires-Dist: MarkupSafe (>=0.23)
Requires-Dist: matplotlib (>=2.0.0)
Requires-Dist: numpy (>=1.12.0)
Requires-Dist: olefile (>=0.44)
Requires-Dist: packaging (>=16.8)
Requires-Dist: Pillow (>=4.0.0)
Requires-Dist: protobuf (>=3.2.0)
Requires-Dist: pyparsing (>=2.1.10)
Requires-Dist: python-dateutil (>=2.6.0)
Requires-Dist: pytz (>=2016.10)
Requires-Dist: PyYAML (>=3.12)
Requires-Dist: requests (>=2.13.0)
Requires-Dist: scipy (>=0.18.1)
Requires-Dist: six (>=1.10.0)
Requires-Dist: Werkzeug (>=0.11.15)
Requires-Dist: tensorflow (>=1.0.0)
Provides-Extra: docs
Requires-Dist: Sphinx; extra == 'docs'
Requires-Dist: sphinxcontrib-napoleon; extra == 'docs'
Requires-Dist: sphinx-rtd-theme; extra == 'docs'
Provides-Extra: test
Requires-Dist: pytest; extra == 'test'
Requires-Dist: pytest-flask; extra == 'test'
